forgejo_bot_guard/__init__.py
forgejo_bot_guard/main.py
forgejo_bot_guard/prompts.py
forgejo_bot_guard-2025.12.21161612.dist-info/METADATA
forgejo_bot_guard-2025.12.21161612.dist-info/WHEEL
forgejo_bot_guard-2025.12.21161612.dist-info/top_level.txt
forgejo_bot_guard-2025.12.21161612.dist-info/RECORD
