Metadata-Version: 2.4
Name: forgejo-bot-guard
Version: 2025.12.21161612
Summary: This package helps administrators of Forgejo (or Git hosting platforms) generate clear, actionable anti-crawling measures by analyzing user-provided text inputs. When given a description of suspicious
Author-email: forgejo-bot-guard <hi@eugene.plus>
License: MIT
Project-URL: Homepage, https://github.com/chigwell/forgejo-bot-guard
Requires-Python: >=3.9
Requires-Dist: langchain-llm7>=0.0.0
Requires-Dist: llmatch-messages>=0.0.0
Requires-Dist: langchain-core>=0.3.0
